[{"unique_id":"Atlanta-Sandy Springs-Roswell, GA Accounting","state":"GA","msa":"Atlanta-Sandy Springs-Roswell","state_and_msa":"Atlanta-Sandy Springs-Roswell, GA","area_code":12060,"occupation":"Accounting","median_hourly_wage":34.51,"hires":1,"hours":40,"savings":0,"annual_cost":0,"occupation_slug":"accounting"},{"unique_id":"Atlanta-Sandy Springs-Roswell, GA Customer Service","state":"GA","msa":"Atlanta-Sandy Springs-Roswell","state_and_msa":"Atlanta-Sandy Springs-Roswell, GA","area_code":12060,"occupation":"Customer Service","median_hourly_wage":16.75,"hires":1,"hours":40,"savings":0,"annual_cost":0,"occupation_slug":"customer_service"},{"unique_id":"Atlanta-Sandy Springs-Roswell, GA Engineering","state":"GA","msa":"Atlanta-Sandy Springs-Roswell","state_and_msa":"Atlanta-Sandy Springs-Roswell, GA","area_code":12060,"occupation":"Engineering","median_hourly_wage":38.198192,"hires":1,"hours":40,"savings":0,"annual_cost":0,"occupation_slug":"engineering"},{"unique_id":"Atlanta-Sandy Springs-Roswell, GA Graphics & Design","state":"GA","msa":"Atlanta-Sandy Springs-Roswell","state_and_msa":"Atlanta-Sandy Springs-Roswell, GA","area_code":12060,"occupation":"Graphics & Design","median_hourly_wage":28.154676,"hires":1,"hours":40,"savings":0,"annual_cost":0,"occupation_slug":"graphics_and_design"},{"unique_id":"Atlanta-Sandy Springs-Roswell, GA Human Resources","state":"GA","msa":"Atlanta-Sandy Springs-Roswell","state_and_msa":"Atlanta-Sandy Springs-Roswell, GA","area_code":12060,"occupation":"Human Resources","median_hourly_wage":32.181534,"hires":1,"hours":40,"savings":0,"annual_cost":0,"occupation_slug":"human_resources"},{"unique_id":"Atlanta-Sandy Springs-Roswell, GA Law","state":"GA","msa":"Atlanta-Sandy Springs-Roswell","state_and_msa":"Atlanta-Sandy Springs-Roswell, GA","area_code":12060,"occupation":"Law","median_hourly_wage":55.01,"hires":1,"hours":40,"savings":0,"annual_cost":0,"occupation_slug":"law"},{"unique_id":"Atlanta-Sandy Springs-Roswell, GA Management Consulting","state":"GA","msa":"Atlanta-Sandy Springs-Roswell","state_and_msa":"Atlanta-Sandy Springs-Roswell, GA","area_code":12060,"occupation":"Management Consulting","median_hourly_wage":39.91,"hires":1,"hours":40,"savings":0,"annual_cost":0,"occupation_slug":"management_consulting"},{"unique_id":"Atlanta-Sandy Springs-Roswell, GA Marketing","state":"GA","msa":"Atlanta-Sandy Springs-Roswell","state_and_msa":"Atlanta-Sandy Springs-Roswell, GA","area_code":12060,"occupation":"Marketing","median_hourly_wage":40.446563,"hires":1,"hours":40,"savings":0,"annual_cost":0,"occupation_slug":"marketing"},{"unique_id":"Atlanta-Sandy Springs-Roswell, GA Network & System Administration","state":"GA","msa":"Atlanta-Sandy Springs-Roswell","state_and_msa":"Atlanta-Sandy Springs-Roswell, GA","area_code":12060,"occupation":"Network & System Administration","median_hourly_wage":41.69,"hires":1,"hours":40,"savings":0,"annual_cost":0,"occupation_slug":"network_and_system_administration"},{"unique_id":"Atlanta-Sandy Springs-Roswell, GA Personal\/Virtual Assistant","state":"GA","msa":"Atlanta-Sandy Springs-Roswell","state_and_msa":"Atlanta-Sandy Springs-Roswell, GA","area_code":12060,"occupation":"Personal\/Virtual Assistant","median_hourly_wage":17.03,"hires":1,"hours":40,"savings":0,"annual_cost":0,"occupation_slug":"personalvirtual_assistant"},{"unique_id":"Atlanta-Sandy Springs-Roswell, GA Public Relations","state":"GA","msa":"Atlanta-Sandy Springs-Roswell","state_and_msa":"Atlanta-Sandy Springs-Roswell, GA","area_code":12060,"occupation":"Public Relations","median_hourly_wage":34.793202,"hires":1,"hours":40,"savings":0,"annual_cost":0,"occupation_slug":"public_relations"},{"unique_id":"Atlanta-Sandy Springs-Roswell, GA Technical Support","state":"GA","msa":"Atlanta-Sandy Springs-Roswell","state_and_msa":"Atlanta-Sandy Springs-Roswell, GA","area_code":12060,"occupation":"Technical Support","median_hourly_wage":24.84,"hires":1,"hours":40,"savings":0,"annual_cost":0,"occupation_slug":"technical_support"},{"unique_id":"Atlanta-Sandy Springs-Roswell, GA Web, Mobile, & Software Dev","state":"GA","msa":"Atlanta-Sandy Springs-Roswell","state_and_msa":"Atlanta-Sandy Springs-Roswell, GA","area_code":12060,"occupation":"Web, Mobile, & Software Dev","median_hourly_wage":48.31147,"hires":1,"hours":40,"savings":0,"annual_cost":0,"occupation_slug":"web_mobile_and_software_dev"}]