[{"unique_id":"Colorado Springs, CO Accounting","state":"CO","msa":"Colorado Springs","state_and_msa":"Colorado Springs, CO","area_code":17820,"occupation":"Accounting","median_hourly_wage":34.43,"hires":1,"hours":40,"occupation_slug":"accounting"},{"unique_id":"Colorado Springs, CO Customer Service","state":"CO","msa":"Colorado Springs","state_and_msa":"Colorado Springs, CO","area_code":17820,"occupation":"Customer Service","median_hourly_wage":14.33,"hires":1,"hours":40,"occupation_slug":"customer_service"},{"unique_id":"Colorado Springs, CO Engineering","state":"CO","msa":"Colorado Springs","state_and_msa":"Colorado Springs, CO","area_code":17820,"occupation":"Engineering","median_hourly_wage":42.115206,"hires":1,"hours":40,"occupation_slug":"engineering"},{"unique_id":"Colorado Springs, CO Graphics & Design","state":"CO","msa":"Colorado Springs","state_and_msa":"Colorado Springs, CO","area_code":17820,"occupation":"Graphics & Design","median_hourly_wage":23.799231,"hires":1,"hours":40,"occupation_slug":"graphics_and_design"},{"unique_id":"Colorado Springs, CO Human Resources","state":"CO","msa":"Colorado Springs","state_and_msa":"Colorado Springs, CO","area_code":17820,"occupation":"Human Resources","median_hourly_wage":30.342895,"hires":1,"hours":40,"occupation_slug":"human_resources"},{"unique_id":"Colorado Springs, CO Law","state":"CO","msa":"Colorado Springs","state_and_msa":"Colorado Springs, CO","area_code":17820,"occupation":"Law","median_hourly_wage":41.73,"hires":1,"hours":40,"occupation_slug":"law"},{"unique_id":"Colorado Springs, CO Management Consulting","state":"CO","msa":"Colorado Springs","state_and_msa":"Colorado Springs, CO","area_code":17820,"occupation":"Management Consulting","median_hourly_wage":41.6,"hires":1,"hours":40,"occupation_slug":"management_consulting"},{"unique_id":"Colorado Springs, CO Marketing","state":"CO","msa":"Colorado Springs","state_and_msa":"Colorado Springs, CO","area_code":17820,"occupation":"Marketing","median_hourly_wage":34.556587,"hires":1,"hours":40,"occupation_slug":"marketing"},{"unique_id":"Colorado Springs, CO Network & System Administration","state":"CO","msa":"Colorado Springs","state_and_msa":"Colorado Springs, CO","area_code":17820,"occupation":"Network & System Administration","median_hourly_wage":36.05,"hires":1,"hours":40,"occupation_slug":"network_and_system_administration"},{"unique_id":"Colorado Springs, CO Personal\/Virtual Assistant","state":"CO","msa":"Colorado Springs","state_and_msa":"Colorado Springs, CO","area_code":17820,"occupation":"Personal\/Virtual Assistant","median_hourly_wage":16.46,"hires":1,"hours":40,"occupation_slug":"personalvirtual_assistant"},{"unique_id":"Colorado Springs, CO Public Relations","state":"CO","msa":"Colorado Springs","state_and_msa":"Colorado Springs, CO","area_code":17820,"occupation":"Public Relations","median_hourly_wage":31.348475,"hires":1,"hours":40,"occupation_slug":"public_relations"},{"unique_id":"Colorado Springs, CO Technical Support","state":"CO","msa":"Colorado Springs","state_and_msa":"Colorado Springs, CO","area_code":17820,"occupation":"Technical Support","median_hourly_wage":24.33,"hires":1,"hours":40,"occupation_slug":"technical_support"},{"unique_id":"Colorado Springs, CO Web, Mobile, & Software Dev","state":"CO","msa":"Colorado Springs","state_and_msa":"Colorado Springs, CO","area_code":17820,"occupation":"Web, Mobile, & Software Dev","median_hourly_wage":49.179295,"hires":1,"hours":40,"occupation_slug":"web_mobile_and_software_dev"}]