[{"unique_id":"Lima, OH Accounting","state":"OH","msa":"Lima","state_and_msa":"Lima, OH","area_code":30620,"occupation":"Accounting","median_hourly_wage":30.16,"hires":1,"hours":40,"occupation_slug":"accounting"},{"unique_id":"Lima, OH Customer Service","state":"OH","msa":"Lima","state_and_msa":"Lima, OH","area_code":30620,"occupation":"Customer Service","median_hourly_wage":14.5,"hires":1,"hours":40,"occupation_slug":"customer_service"},{"unique_id":"Lima, OH Engineering","state":"OH","msa":"Lima","state_and_msa":"Lima, OH","area_code":30620,"occupation":"Engineering","median_hourly_wage":42.121667,"hires":1,"hours":40,"occupation_slug":"engineering"},{"unique_id":"Lima, OH Human Resources","state":"OH","msa":"Lima","state_and_msa":"Lima, OH","area_code":30620,"occupation":"Human Resources","median_hourly_wage":24.627143,"hires":1,"hours":40,"occupation_slug":"human_resources"},{"unique_id":"Lima, OH Law","state":"OH","msa":"Lima","state_and_msa":"Lima, OH","area_code":30620,"occupation":"Law","median_hourly_wage":28.9,"hires":1,"hours":40,"occupation_slug":"law"},{"unique_id":"Lima, OH Marketing","state":"OH","msa":"Lima","state_and_msa":"Lima, OH","area_code":30620,"occupation":"Marketing","median_hourly_wage":20.96,"hires":1,"hours":40,"occupation_slug":"marketing"},{"unique_id":"Lima, OH Network & System Administration","state":"OH","msa":"Lima","state_and_msa":"Lima, OH","area_code":30620,"occupation":"Network & System Administration","median_hourly_wage":31,"hires":1,"hours":40,"occupation_slug":"network_and_system_administration"},{"unique_id":"Lima, OH Personal\/Virtual Assistant","state":"OH","msa":"Lima","state_and_msa":"Lima, OH","area_code":30620,"occupation":"Personal\/Virtual Assistant","median_hourly_wage":14.97,"hires":1,"hours":40,"occupation_slug":"personalvirtual_assistant"},{"unique_id":"Lima, OH Public Relations","state":"OH","msa":"Lima","state_and_msa":"Lima, OH","area_code":30620,"occupation":"Public Relations","median_hourly_wage":22.44,"hires":1,"hours":40,"occupation_slug":"public_relations"},{"unique_id":"Lima, OH Technical Support","state":"OH","msa":"Lima","state_and_msa":"Lima, OH","area_code":30620,"occupation":"Technical Support","median_hourly_wage":19.93,"hires":1,"hours":40,"occupation_slug":"technical_support"}]