[{"unique_id":"Northeast Nebraska nonmetropolitan area, NE Accounting","state":"NE","msa":"Northeast Nebraska nonmetropolitan area","state_and_msa":"Northeast Nebraska nonmetropolitan area, NE","area_code":3100003,"occupation":"Accounting","median_hourly_wage":26.37,"hires":1,"hours":40,"savings":0,"annual_cost":0,"occupation_slug":"accounting"},{"unique_id":"Northeast Nebraska nonmetropolitan area, NE Customer Service","state":"NE","msa":"Northeast Nebraska nonmetropolitan area","state_and_msa":"Northeast Nebraska nonmetropolitan area, NE","area_code":3100003,"occupation":"Customer Service","median_hourly_wage":13.71,"hires":1,"hours":40,"savings":0,"annual_cost":0,"occupation_slug":"customer_service"},{"unique_id":"Northeast Nebraska nonmetropolitan area, NE Engineering","state":"NE","msa":"Northeast Nebraska nonmetropolitan area","state_and_msa":"Northeast Nebraska nonmetropolitan area, NE","area_code":3100003,"occupation":"Engineering","median_hourly_wage":33.298667,"hires":1,"hours":40,"savings":0,"annual_cost":0,"occupation_slug":"engineering"},{"unique_id":"Northeast Nebraska nonmetropolitan area, NE Graphics & Design","state":"NE","msa":"Northeast Nebraska nonmetropolitan area","state_and_msa":"Northeast Nebraska nonmetropolitan area, NE","area_code":3100003,"occupation":"Graphics & Design","median_hourly_wage":15.22,"hires":1,"hours":40,"savings":0,"annual_cost":0,"occupation_slug":"graphics_and_design"},{"unique_id":"Northeast Nebraska nonmetropolitan area, NE Human Resources","state":"NE","msa":"Northeast Nebraska nonmetropolitan area","state_and_msa":"Northeast Nebraska nonmetropolitan area, NE","area_code":3100003,"occupation":"Human Resources","median_hourly_wage":25.566,"hires":1,"hours":40,"savings":0,"annual_cost":0,"occupation_slug":"human_resources"},{"unique_id":"Northeast Nebraska nonmetropolitan area, NE Law","state":"NE","msa":"Northeast Nebraska nonmetropolitan area","state_and_msa":"Northeast Nebraska nonmetropolitan area, NE","area_code":3100003,"occupation":"Law","median_hourly_wage":29.72,"hires":1,"hours":40,"savings":0,"annual_cost":0,"occupation_slug":"law"},{"unique_id":"Northeast Nebraska nonmetropolitan area, NE Management Consulting","state":"NE","msa":"Northeast Nebraska nonmetropolitan area","state_and_msa":"Northeast Nebraska nonmetropolitan area, NE","area_code":3100003,"occupation":"Management Consulting","median_hourly_wage":37.2,"hires":1,"hours":40,"savings":0,"annual_cost":0,"occupation_slug":"management_consulting"},{"unique_id":"Northeast Nebraska nonmetropolitan area, NE Marketing","state":"NE","msa":"Northeast Nebraska nonmetropolitan area","state_and_msa":"Northeast Nebraska nonmetropolitan area, NE","area_code":3100003,"occupation":"Marketing","median_hourly_wage":25.14,"hires":1,"hours":40,"savings":0,"annual_cost":0,"occupation_slug":"marketing"},{"unique_id":"Northeast Nebraska nonmetropolitan area, NE Network & System Administration","state":"NE","msa":"Northeast Nebraska nonmetropolitan area","state_and_msa":"Northeast Nebraska nonmetropolitan area, NE","area_code":3100003,"occupation":"Network & System Administration","median_hourly_wage":30.67,"hires":1,"hours":40,"savings":0,"annual_cost":0,"occupation_slug":"network_and_system_administration"},{"unique_id":"Northeast Nebraska nonmetropolitan area, NE Personal\/Virtual Assistant","state":"NE","msa":"Northeast Nebraska nonmetropolitan area","state_and_msa":"Northeast Nebraska nonmetropolitan area, NE","area_code":3100003,"occupation":"Personal\/Virtual Assistant","median_hourly_wage":14.85,"hires":1,"hours":40,"savings":0,"annual_cost":0,"occupation_slug":"personalvirtual_assistant"},{"unique_id":"Northeast Nebraska nonmetropolitan area, NE Public Relations","state":"NE","msa":"Northeast Nebraska nonmetropolitan area","state_and_msa":"Northeast Nebraska nonmetropolitan area, NE","area_code":3100003,"occupation":"Public Relations","median_hourly_wage":27.53,"hires":1,"hours":40,"savings":0,"annual_cost":0,"occupation_slug":"public_relations"},{"unique_id":"Northeast Nebraska nonmetropolitan area, NE Technical Support","state":"NE","msa":"Northeast Nebraska nonmetropolitan area","state_and_msa":"Northeast Nebraska nonmetropolitan area, NE","area_code":3100003,"occupation":"Technical Support","median_hourly_wage":24.02,"hires":1,"hours":40,"savings":0,"annual_cost":0,"occupation_slug":"technical_support"}]