[{"unique_id":"Madison, WI Accounting","state":"WI","msa":"Madison","state_and_msa":"Madison, WI","area_code":31540,"occupation":"Accounting","median_hourly_wage":31.24,"hires":1,"hours":40,"savings":0,"annual_cost":0,"occupation_slug":"accounting"},{"unique_id":"Madison, WI Customer Service","state":"WI","msa":"Madison","state_and_msa":"Madison, WI","area_code":31540,"occupation":"Customer Service","median_hourly_wage":17.66,"hires":1,"hours":40,"savings":0,"annual_cost":0,"occupation_slug":"customer_service"},{"unique_id":"Madison, WI Engineering","state":"WI","msa":"Madison","state_and_msa":"Madison, WI","area_code":31540,"occupation":"Engineering","median_hourly_wage":37.589024,"hires":1,"hours":40,"savings":0,"annual_cost":0,"occupation_slug":"engineering"},{"unique_id":"Madison, WI Graphics & Design","state":"WI","msa":"Madison","state_and_msa":"Madison, WI","area_code":31540,"occupation":"Graphics & Design","median_hourly_wage":25.325631,"hires":1,"hours":40,"savings":0,"annual_cost":0,"occupation_slug":"graphics_and_design"},{"unique_id":"Madison, WI Human Resources","state":"WI","msa":"Madison","state_and_msa":"Madison, WI","area_code":31540,"occupation":"Human Resources","median_hourly_wage":31.066548,"hires":1,"hours":40,"savings":0,"annual_cost":0,"occupation_slug":"human_resources"},{"unique_id":"Madison, WI Law","state":"WI","msa":"Madison","state_and_msa":"Madison, WI","area_code":31540,"occupation":"Law","median_hourly_wage":49.77,"hires":1,"hours":40,"savings":0,"annual_cost":0,"occupation_slug":"law"},{"unique_id":"Madison, WI Management Consulting","state":"WI","msa":"Madison","state_and_msa":"Madison, WI","area_code":31540,"occupation":"Management Consulting","median_hourly_wage":35.29,"hires":1,"hours":40,"savings":0,"annual_cost":0,"occupation_slug":"management_consulting"},{"unique_id":"Madison, WI Marketing","state":"WI","msa":"Madison","state_and_msa":"Madison, WI","area_code":31540,"occupation":"Marketing","median_hourly_wage":32.382651,"hires":1,"hours":40,"savings":0,"annual_cost":0,"occupation_slug":"marketing"},{"unique_id":"Madison, WI Network & System Administration","state":"WI","msa":"Madison","state_and_msa":"Madison, WI","area_code":31540,"occupation":"Network & System Administration","median_hourly_wage":39.72,"hires":1,"hours":40,"savings":0,"annual_cost":0,"occupation_slug":"network_and_system_administration"},{"unique_id":"Madison, WI Personal\/Virtual Assistant","state":"WI","msa":"Madison","state_and_msa":"Madison, WI","area_code":31540,"occupation":"Personal\/Virtual Assistant","median_hourly_wage":18.25,"hires":1,"hours":40,"savings":0,"annual_cost":0,"occupation_slug":"personalvirtual_assistant"},{"unique_id":"Madison, WI Public Relations","state":"WI","msa":"Madison","state_and_msa":"Madison, WI","area_code":31540,"occupation":"Public Relations","median_hourly_wage":32.059784,"hires":1,"hours":40,"savings":0,"annual_cost":0,"occupation_slug":"public_relations"},{"unique_id":"Madison, WI Technical Support","state":"WI","msa":"Madison","state_and_msa":"Madison, WI","area_code":31540,"occupation":"Technical Support","median_hourly_wage":26.53,"hires":1,"hours":40,"savings":0,"annual_cost":0,"occupation_slug":"technical_support"},{"unique_id":"Madison, WI Web, Mobile, & Software Dev","state":"WI","msa":"Madison","state_and_msa":"Madison, WI","area_code":31540,"occupation":"Web, Mobile, & Software Dev","median_hourly_wage":39.72,"hires":1,"hours":40,"savings":0,"annual_cost":0,"occupation_slug":"web_mobile_and_software_dev"}]