[{"unique_id":"Medford, OR Accounting","state":"OR","msa":"Medford","state_and_msa":"Medford, OR","area_code":32780,"occupation":"Accounting","median_hourly_wage":29.56,"hires":1,"hours":40,"savings":0,"annual_cost":0,"occupation_slug":"accounting"},{"unique_id":"Medford, OR Customer Service","state":"OR","msa":"Medford","state_and_msa":"Medford, OR","area_code":32780,"occupation":"Customer Service","median_hourly_wage":15.7,"hires":1,"hours":40,"savings":0,"annual_cost":0,"occupation_slug":"customer_service"},{"unique_id":"Medford, OR Engineering","state":"OR","msa":"Medford","state_and_msa":"Medford, OR","area_code":32780,"occupation":"Engineering","median_hourly_wage":35.818571,"hires":1,"hours":40,"savings":0,"annual_cost":0,"occupation_slug":"engineering"},{"unique_id":"Medford, OR Graphics & Design","state":"OR","msa":"Medford","state_and_msa":"Medford, OR","area_code":32780,"occupation":"Graphics & Design","median_hourly_wage":21.7,"hires":1,"hours":40,"savings":0,"annual_cost":0,"occupation_slug":"graphics_and_design"},{"unique_id":"Medford, OR Human Resources","state":"OR","msa":"Medford","state_and_msa":"Medford, OR","area_code":32780,"occupation":"Human Resources","median_hourly_wage":29.045,"hires":1,"hours":40,"savings":0,"annual_cost":0,"occupation_slug":"human_resources"},{"unique_id":"Medford, OR Law","state":"OR","msa":"Medford","state_and_msa":"Medford, OR","area_code":32780,"occupation":"Law","median_hourly_wage":54.29,"hires":1,"hours":40,"savings":0,"annual_cost":0,"occupation_slug":"law"},{"unique_id":"Medford, OR Management Consulting","state":"OR","msa":"Medford","state_and_msa":"Medford, OR","area_code":32780,"occupation":"Management Consulting","median_hourly_wage":39.43,"hires":1,"hours":40,"savings":0,"annual_cost":0,"occupation_slug":"management_consulting"},{"unique_id":"Medford, OR Marketing","state":"OR","msa":"Medford","state_and_msa":"Medford, OR","area_code":32780,"occupation":"Marketing","median_hourly_wage":30.234615,"hires":1,"hours":40,"savings":0,"annual_cost":0,"occupation_slug":"marketing"},{"unique_id":"Medford, OR Network & System Administration","state":"OR","msa":"Medford","state_and_msa":"Medford, OR","area_code":32780,"occupation":"Network & System Administration","median_hourly_wage":33.06,"hires":1,"hours":40,"savings":0,"annual_cost":0,"occupation_slug":"network_and_system_administration"},{"unique_id":"Medford, OR Personal\/Virtual Assistant","state":"OR","msa":"Medford","state_and_msa":"Medford, OR","area_code":32780,"occupation":"Personal\/Virtual Assistant","median_hourly_wage":17.05,"hires":1,"hours":40,"savings":0,"annual_cost":0,"occupation_slug":"personalvirtual_assistant"},{"unique_id":"Medford, OR Public Relations","state":"OR","msa":"Medford","state_and_msa":"Medford, OR","area_code":32780,"occupation":"Public Relations","median_hourly_wage":32.452,"hires":1,"hours":40,"savings":0,"annual_cost":0,"occupation_slug":"public_relations"},{"unique_id":"Medford, OR Technical Support","state":"OR","msa":"Medford","state_and_msa":"Medford, OR","area_code":32780,"occupation":"Technical Support","median_hourly_wage":23.05,"hires":1,"hours":40,"savings":0,"annual_cost":0,"occupation_slug":"technical_support"},{"unique_id":"Medford, OR Web, Mobile, & Software Dev","state":"OR","msa":"Medford","state_and_msa":"Medford, OR","area_code":32780,"occupation":"Web, Mobile, & Software Dev","median_hourly_wage":31.818,"hires":1,"hours":40,"savings":0,"annual_cost":0,"occupation_slug":"web_mobile_and_software_dev"}]