[{"unique_id":"East South Dakota nonmetropolitan area, SD Accounting","state":"SD","msa":"East South Dakota nonmetropolitan area","state_and_msa":"East South Dakota nonmetropolitan area, SD","area_code":4600002,"occupation":"Accounting","median_hourly_wage":29.48,"hires":1,"hours":40,"occupation_slug":"accounting"},{"unique_id":"East South Dakota nonmetropolitan area, SD Customer Service","state":"SD","msa":"East South Dakota nonmetropolitan area","state_and_msa":"East South Dakota nonmetropolitan area, SD","area_code":4600002,"occupation":"Customer Service","median_hourly_wage":14.18,"hires":1,"hours":40,"occupation_slug":"customer_service"},{"unique_id":"East South Dakota nonmetropolitan area, SD Engineering","state":"SD","msa":"East South Dakota nonmetropolitan area","state_and_msa":"East South Dakota nonmetropolitan area, SD","area_code":4600002,"occupation":"Engineering","median_hourly_wage":33.333014,"hires":1,"hours":40,"occupation_slug":"engineering"},{"unique_id":"East South Dakota nonmetropolitan area, SD Graphics & Design","state":"SD","msa":"East South Dakota nonmetropolitan area","state_and_msa":"East South Dakota nonmetropolitan area, SD","area_code":4600002,"occupation":"Graphics & Design","median_hourly_wage":15.53,"hires":1,"hours":40,"occupation_slug":"graphics_and_design"},{"unique_id":"East South Dakota nonmetropolitan area, SD Human Resources","state":"SD","msa":"East South Dakota nonmetropolitan area","state_and_msa":"East South Dakota nonmetropolitan area, SD","area_code":4600002,"occupation":"Human Resources","median_hourly_wage":26.575128,"hires":1,"hours":40,"occupation_slug":"human_resources"},{"unique_id":"East South Dakota nonmetropolitan area, SD Law","state":"SD","msa":"East South Dakota nonmetropolitan area","state_and_msa":"East South Dakota nonmetropolitan area, SD","area_code":4600002,"occupation":"Law","median_hourly_wage":35.51,"hires":1,"hours":40,"occupation_slug":"law"},{"unique_id":"East South Dakota nonmetropolitan area, SD Management Consulting","state":"SD","msa":"East South Dakota nonmetropolitan area","state_and_msa":"East South Dakota nonmetropolitan area, SD","area_code":4600002,"occupation":"Management Consulting","median_hourly_wage":33.05,"hires":1,"hours":40,"occupation_slug":"management_consulting"},{"unique_id":"East South Dakota nonmetropolitan area, SD Marketing","state":"SD","msa":"East South Dakota nonmetropolitan area","state_and_msa":"East South Dakota nonmetropolitan area, SD","area_code":4600002,"occupation":"Marketing","median_hourly_wage":23.99,"hires":1,"hours":40,"occupation_slug":"marketing"},{"unique_id":"East South Dakota nonmetropolitan area, SD Network & System Administration","state":"SD","msa":"East South Dakota nonmetropolitan area","state_and_msa":"East South Dakota nonmetropolitan area, SD","area_code":4600002,"occupation":"Network & System Administration","median_hourly_wage":28.1,"hires":1,"hours":40,"occupation_slug":"network_and_system_administration"},{"unique_id":"East South Dakota nonmetropolitan area, SD Personal\/Virtual Assistant","state":"SD","msa":"East South Dakota nonmetropolitan area","state_and_msa":"East South Dakota nonmetropolitan area, SD","area_code":4600002,"occupation":"Personal\/Virtual Assistant","median_hourly_wage":13.82,"hires":1,"hours":40,"occupation_slug":"personalvirtual_assistant"},{"unique_id":"East South Dakota nonmetropolitan area, SD Public Relations","state":"SD","msa":"East South Dakota nonmetropolitan area","state_and_msa":"East South Dakota nonmetropolitan area, SD","area_code":4600002,"occupation":"Public Relations","median_hourly_wage":23.52,"hires":1,"hours":40,"occupation_slug":"public_relations"},{"unique_id":"East South Dakota nonmetropolitan area, SD Technical Support","state":"SD","msa":"East South Dakota nonmetropolitan area","state_and_msa":"East South Dakota nonmetropolitan area, SD","area_code":4600002,"occupation":"Technical Support","median_hourly_wage":18.23,"hires":1,"hours":40,"occupation_slug":"technical_support"},{"unique_id":"East South Dakota nonmetropolitan area, SD Web, Mobile, & Software Dev","state":"SD","msa":"East South Dakota nonmetropolitan area","state_and_msa":"East South Dakota nonmetropolitan area, SD","area_code":4600002,"occupation":"Web, Mobile, & Software Dev","median_hourly_wage":31.386667,"hires":1,"hours":40,"occupation_slug":"web_mobile_and_software_dev"}]